tvorozhok/__init__.py
tvorozhok/cli.py
tvorozhok/main.py
tvorozhok/tvorozhok.py
tvorozhok/tvorozhok_bot.py
tvorozhok-0.2.0.dist-info/METADATA
tvorozhok-0.2.0.dist-info/WHEEL
tvorozhok-0.2.0.dist-info/entry_points.txt
tvorozhok-0.2.0.dist-info/top_level.txt
tvorozhok-0.2.0.dist-info/RECORD
